tripleo_validations/__init__.py
tripleo_validations/utils.py
tripleo_validations/tests/__init__.py
tripleo_validations/tests/base.py
tripleo_validations/tests/fakes.py
tripleo_validations/tests/test_utils.py
tripleo_validations/tests/library/__init__.py
tripleo_validations/tests/library/test_ceph_pools_pg_protection.py
tripleo_validations/tests/library/test_check_cpus_aligned_with_dpdk_nics.py
tripleo_validations/tests/library/test_check_flavors.py
tripleo_validations/tests/library/test_check_ironic_boot_config.py
tripleo_validations/tests/library/test_check_other_processes_pmd_usage.py
tripleo_validations/tests/library/test_convert_range_to_numbers_list.py
tripleo_validations/tests/library/test_get_dpdk_nics_numa_info.py
tripleo_validations/tests/library/test_icmp_ping.py
tripleo_validations/tests/library/test_ip_range.py
tripleo_validations/tests/library/test_network_environment.py
tripleo_validations/tests/library/test_node_disks.py
tripleo_validations/tests/library/test_ovs_dpdk_pmd_cpus_check.py
tripleo_validations/tests/library/test_pacemaker.py
tripleo_validations/tests/library/test_pmd_threads_siblings_check.py
tripleo_validations/tests/library/test_switch_vlans.py
tripleo_validations/tests/library/test_tripleo_haproxy_conf.py
tripleo_validations/tests/library/test_verify_profiles.py
tripleo_validations/tests/lookup_plugins/__init__.py
tripleo_validations/tests/lookup_plugins/test_glance_images.py
tripleo_validations/tests/lookup_plugins/test_introspection_data.py
tripleo_validations/tests/lookup_plugins/test_ironic_nodes.py
tripleo_validations/tests/lookup_plugins/test_nova_flavors.py
tripleo_validations/tests/lookup_plugins/test_nova_hypervisor_statistics.py
tripleo_validations/tests/lookup_plugins/test_nova_servers.py
tripleo_validations/tests/lookup_plugins/test_roles_info.py
tripleo_validations/tests/lookup_plugins/test_stack_resources.py
tripleo_validations/tests/lookup_plugins/test_tht.py
tripleo_validations-16.0.0.data/data/share/ansible/groups.yaml
tripleo_validations-16.0.0.dist-info/AUTHORS
tripleo_validations-16.0.0.dist-info/LICENSE
tripleo_validations-16.0.0.dist-info/METADATA
tripleo_validations-16.0.0.dist-info/WHEEL
tripleo_validations-16.0.0.dist-info/pbr.json
tripleo_validations-16.0.0.dist-info/top_level.txt
tripleo_validations-16.0.0.dist-info/RECORD
