Metadata-Version: 2.1
Name: tripleo-validations
Version: 16.0.0
Summary: A collection of Ansible playbooks to detect and report potential issues during TripleO deployments
Home-page: https://docs.openstack.org/tripleo-validations/latest/
Author: OpenStack
Author-email: openstack-discuss@lists.openstack.org
License: UNKNOWN
Platform: UNKNOWN
Classifier: Development Status :: 5 - Production/Stable
Classifier: Environment :: OpenStack
Classifier: Framework :: Ansible
Classifier: Intended Audience :: Information Technology
Classifier: Intended Audience :: System Administrators
Classifier: License :: OSI Approved :: Apache Software License
Classifier: Operating System :: POSIX :: Linux
Classifier: Programming Language :: Python
Classifier: Programming Language :: Python :: Implementation :: CPython
Classifier: Programming Language :: Python :: 3 :: Only
Classifier: Programming Language :: Python :: 3
Classifier: Programming Language :: Python :: 3.8
Requires-Python: >=3.8
Requires-Dist: keystoneauth1 (>=3.16.0)
Requires-Dist: os-net-config (>=7.1.0)
Requires-Dist: oslo.config (>=5.2.0)
Requires-Dist: oslo.utils (>=3.40.2)
Requires-Dist: pbr (>=3.1.1)
Requires-Dist: python-glanceclient (>=2.9.1)
Requires-Dist: python-heatclient (>=1.10.0)
Requires-Dist: python-ironic-inspector-client (>=3.1.1)
Requires-Dist: python-ironicclient (>=2.7.0)
Requires-Dist: python-novaclient (>=15.1.0)
Requires-Dist: setuptools (>=50.3.0)
Requires-Dist: six (>=1.11.0)
Requires-Dist: tripleo-common (>=7.1.0)
